apb_slave_dut.sv
//=====================================================================
// apb_slave_dut.sv
// Simple APB Slave: 16 x 32-bit addressable registers
// Includes a couple of intentional quirks that a good randomized
// testbench (and NOT a directed one) is likely to catch:
//   1. Register 0xF (READ-ONLY status reg) ignores writes.
//   2. Writing to an out-of-range address sets PSLVERR.
//   3. Register 0x0 clears itself 2 cycles after being written with
//      bit[31] set (models a "self-clearing control bit" - classic
//      register bug source).
//=====================================================================
module apb_slave_dut #(
    parameter ADDR_WIDTH = 8,
    parameter DATA_WIDTH = 32
)(
    input  logic                    pclk,
    input  logic                    presetn,
    input  logic [ADDR_WIDTH-1:0]   paddr,
    input  logic                    pwrite,
    input  logic                    psel,
    input  logic                    penable,
    input  logic [DATA_WIDTH-1:0]   pwdata,
    output logic [DATA_WIDTH-1:0]   prdata,
    output logic                    pready,
    output logic                    pslverr
);

    localparam NUM_REGS = 16;
    logic [DATA_WIDTH-1:0] regs [0:NUM_REGS-1];
    logic [1:0] self_clear_cnt;

    wire [3:0] reg_idx = paddr[5:2]; // word-aligned decode
    wire       in_range = (paddr < (NUM_REGS*4));

    // APB FSM: single-cycle ready (no wait states) for simplicity
    always_ff @(posedge pclk or negedge presetn) begin
        if (!presetn) begin
            for (int i = 0; i < NUM_REGS; i++) regs[i] <= '0;
            prdata         <= '0;
            pslverr        <= 1'b0;
            self_clear_cnt <= '0;
        end else begin
            pslverr <= 1'b0;

            // self-clearing bit logic for reg0
            if (self_clear_cnt != 0) begin
                self_clear_cnt <= self_clear_cnt - 1;
                if (self_clear_cnt == 1)
                    regs[0][31] <= 1'b0;
            end

            if (psel && penable) begin
                if (!in_range) begin
                    pslverr <= 1'b1;
                end else if (pwrite) begin
                    if (reg_idx != 4'hF) begin // reg 0xF is read-only
                        regs[reg_idx] <= pwdata;
                        if (reg_idx == 0 && pwdata[31])
                            self_clear_cnt <= 2'd2;
                    end
                end else begin
                    prdata <= in_range ? regs[reg_idx] : '0;
                end
            end
        end
    end

    assign pready = 1'b1; // no wait-state slave

endmodule

tb_top_iverilog.sv
//=====================================================================
// tb_top_iverilog.sv
// ICARUS-VERILOG-COMPATIBLE VERSION of the APB layered testbench.
//
// WHY THIS FILE EXISTS:
// Icarus Verilog (iverilog) implements only a partial subset of
// SystemVerilog. It does NOT support: constraint blocks, randomize(),
// covergroups, clocking blocks, mailbox/semaphore classes, or virtual
// interfaces as class members. Those ARE supported by the commercial
// simulators used in industry (Questa, VCS, Xcelium) and by EDA
// Playground - which is what the class-based files in this repo
// (apb_transaction.sv, apb_generator.sv, apb_driver.sv, apb_monitor.sv,
// apb_scoreboard.sv, apb_coverage.sv, apb_env.sv) are written for and
// were designed against.
//
// This file re-implements the SAME verification methodology
// (generator, driver, monitor, self-checking scoreboard, functional
// coverage bins, constrained-random stimulus, corner-case biasing)
// using tasks and procedural code instead of classes, purely so it
// can be compiled and run end-to-end on the free, offline Icarus
// Verilog toolchain and produce a real simulation log.
//=====================================================================

module tb_top_iverilog;

    // ---------------------------------------------------------------
    // Clock / reset
    // ---------------------------------------------------------------
    logic pclk;
    logic presetn;

    initial pclk = 0;
    always #5 pclk = ~pclk;

    // ---------------------------------------------------------------
    // DUT signals
    // ---------------------------------------------------------------
    logic [7:0]  paddr;
    logic        pwrite;
    logic        psel;
    logic        penable;
    logic [31:0] pwdata;
    logic [31:0] prdata;
    logic        pready;
    logic        pslverr;

    apb_slave_dut #(.ADDR_WIDTH(8), .DATA_WIDTH(32)) dut (
        .pclk    (pclk),
        .presetn (presetn),
        .paddr   (paddr),
        .pwrite  (pwrite),
        .psel    (psel),
        .penable (penable),
        .pwdata  (pwdata),
        .prdata  (prdata),
        .pready  (pready),
        .pslverr (pslverr)
    );

    // ---------------------------------------------------------------
    // Reference model (mirrors DUT register file for scoreboarding)
    // ---------------------------------------------------------------
    logic [31:0] ref_regs [0:15];

    // ---------------------------------------------------------------
    // Bookkeeping
    // ---------------------------------------------------------------
    int pass_count   = 0;
    int fail_count   = 0;
    int total_txns   = 0;

    // functional coverage bins (manual, since covergroup unsupported)
    int cov_reg0_hits        = 0;
    int cov_normal_reg_hits  = 0;
    int cov_readonly_hits    = 0;
    int cov_oob_hits         = 0;
    int cov_write_count      = 0;
    int cov_read_count       = 0;
    int cov_selfclear_bit_set= 0;
    int cov_pslverr_seen     = 0;

    // ---------------------------------------------------------------
    // Driver task: performs one APB SETUP->ACCESS transfer
    // ---------------------------------------------------------------
    task automatic apb_transfer(
        input  logic [7:0]  addr,
        input  logic        write,
        input  logic [31:0] wdata,
        output logic [31:0] rdata_out,
        output logic        slverr_out
    );
        @(posedge pclk);
        psel    <= 1;
        penable <= 0;
        paddr   <= addr;
        pwrite  <= write;
        pwdata  <= write ? wdata : '0;

        @(posedge pclk);
        penable <= 1;

        @(posedge pclk);
        #1; // let the DUT's nonblocking (NBA) update to prdata/pslverr settle
            // before sampling - without this delay there is a classic
            // read-before-write race (this is exactly the race that SV
            // 'clocking block' input skew, e.g. "input #1step", exists to
            // prevent in the class-based/clocking-block version of this TB)
        rdata_out  = prdata;
        slverr_out = pslverr;

        psel    <= 0;
        penable <= 0;
    endtask

    // ---------------------------------------------------------------
    // Reference-model check (same rules as the DUT, including the
    // register-0 self-clearing bit[31] behavior - see the masking
    // logic in the read branch below for how the timing is modeled)
    // ---------------------------------------------------------------
    task automatic check_txn(
        input logic [7:0]  addr,
        input logic        write,
        input logic [31:0] wdata,
        input logic [31:0] rdata,
        input logic        slverr
    );
        logic [3:0] idx;
        logic       in_range;
        idx      = addr[5:2];
        in_range = (addr < 8'h40);

        total_txns++;
        if (write) cov_write_count++; else cov_read_count++;
        if (slverr) cov_pslverr_seen++;

        if (addr == 8'h00)        cov_reg0_hits++;
        else if (addr == 8'h3C)   cov_readonly_hits++;
        else if (!in_range)       cov_oob_hits++;
        else                      cov_normal_reg_hits++;

        if (write && addr == 8'h00 && wdata[31]) cov_selfclear_bit_set++;

        if (!in_range) begin
            if (slverr) begin
                pass_count++;
            end else begin
                fail_count++;
                $display("[%0t] FAIL: expected PSLVERR for out-of-range addr=0x%0h", $time, addr);
            end
        end else if (write) begin
            if (idx != 4'hF) // read-only reg ignores writes
                ref_regs[idx] = wdata;
            pass_count++;
        end else begin
            logic [31:0] expected;
            expected = ref_regs[idx];
            // Register 0 bit[31] self-clears 2 cycles after being written
            // with bit[31] set. Every APB transaction here takes 3 clock
            // edges (SETUP/ACCESS/sample), so by the time ANY subsequent
            // read transaction occurs, at least one full extra transaction
            // (>= 3 clock edges) has elapsed since the write's ACCESS edge -
            // more than enough for the 2-cycle self-clear to have already
            // completed on real hardware. So a read of reg0 must always
            // expect bit[31] == 0, regardless of what was last written.
            if (idx == 4'h0)
                expected[31] = 1'b0;

            if (rdata === expected) begin
                pass_count++;
            end else begin
                fail_count++;
                $display("[%0t] FAIL: read mismatch addr=0x%0h exp=0x%0h got=0x%0h",
                          $time, addr, expected, rdata);
            end
        end
    endtask

    // ---------------------------------------------------------------
    // Constrained-random-style address generator (manual, replicates
    // the weighted 'target_special_reg dist' constraint from
    // apb_transaction.sv using $urandom_range since Icarus has no
    // 'dist'/'constraint' support)
    // ---------------------------------------------------------------
    function automatic logic [7:0] gen_addr();
        int pick;
        int special_pick;
        pick = $urandom_range(0, 99);
        if (pick < 30) begin
            // 30% of the time: hit a "special" address, matching the
            // {reg0, readonly_reg(0x3C), out-of-range(0x40/0x44)} set
            special_pick = $urandom_range(0, 3);
            case (special_pick)
                0: gen_addr = 8'h00;
                1: gen_addr = 8'h3C;
                2: gen_addr = 8'h40;
                3: gen_addr = 8'h44;
            endcase
        end else begin
            // 70%: normal word-aligned address in range
            gen_addr = {$urandom_range(0, 15), 2'b00};
        end
    endfunction

    // ---------------------------------------------------------------
    // Main stimulus
    // ---------------------------------------------------------------
    logic [31:0] rdata_capture;
    logic        slverr_capture;
    logic [7:0]  addr_capture;
    logic        write_capture;
    logic [31:0] wdata_capture;

    initial begin
        int i;

        for (i = 0; i < 16; i++) ref_regs[i] = '0;

        psel    = 0;
        penable = 0;
        pwrite  = 0;
        paddr   = 0;
        pwdata  = 0;
        presetn = 0;
        repeat (5) @(posedge pclk);
        presetn = 1;
        repeat (3) @(posedge pclk);

        $display("=========================================");
        $display(" APB Layered TB (Icarus-compatible) START");
        $display("=========================================");

        for (i = 0; i < 200; i++) begin
            addr_capture  = gen_addr();
            write_capture = $urandom_range(0, 1);
            wdata_capture = $urandom;

            apb_transfer(addr_capture, write_capture, wdata_capture,
                         rdata_capture, slverr_capture);

            check_txn(addr_capture, write_capture, wdata_capture,
                     rdata_capture, slverr_capture);
        end

        // drain
        repeat (10) @(posedge pclk);

        $display("=========================================");
        $display(" SCOREBOARD REPORT: PASS=%0d FAIL=%0d TOTAL=%0d",
                  pass_count, fail_count, total_txns);
        $display("=========================================");
        $display(" FUNCTIONAL COVERAGE (manual bins)");
        $display("   reg0 hits          : %0d %s", cov_reg0_hits,        (cov_reg0_hits>0)?"[HIT]":"[MISS]");
        $display("   normal_regs hits   : %0d %s", cov_normal_reg_hits,  (cov_normal_reg_hits>0)?"[HIT]":"[MISS]");
        $display("   readonly_reg hits  : %0d %s", cov_readonly_hits,    (cov_readonly_hits>0)?"[HIT]":"[MISS]");
        $display("   out_of_range hits  : %0d %s", cov_oob_hits,         (cov_oob_hits>0)?"[HIT]":"[MISS]");
        $display("   write ops          : %0d %s", cov_write_count,      (cov_write_count>0)?"[HIT]":"[MISS]");
        $display("   read ops           : %0d %s", cov_read_count,       (cov_read_count>0)?"[HIT]":"[MISS]");
        $display("   selfclear bit set  : %0d %s", cov_selfclear_bit_set,(cov_selfclear_bit_set>0)?"[HIT]":"[MISS]");
        $display("   PSLVERR observed   : %0d %s", cov_pslverr_seen,     (cov_pslverr_seen>0)?"[HIT]":"[MISS]");
        $display("=========================================");
        begin
            int bins_hit;
            bins_hit = (cov_reg0_hits>0) + (cov_normal_reg_hits>0) + (cov_readonly_hits>0) +
                       (cov_oob_hits>0) + (cov_write_count>0) + (cov_read_count>0) +
                       (cov_selfclear_bit_set>0) + (cov_pslverr_seen>0);
            $display(" COVERAGE: %0d / 8 bins hit (%0.1f%%)", bins_hit, (bins_hit*100.0)/8.0);
        end
        $display("=========================================");

        if (fail_count == 0)
            $display(" RESULT: ALL TESTS PASSED");
        else
            $display(" RESULT: %0d TEST(S) FAILED", fail_count);

        $display("=========================================");
        $finish;
    end

    // waveform dump
    initial begin
        $dumpfile("apb_tb.vcd");
        $dumpvars(0, tb_top_iverilog);
    end

endmodule

apb_tb.vcd
$date
	Mon Jul 13 20:31:16 2026
$end
$version
	ModelSim Version 2020.1
$end
$timescale
	1ps
$end

$scope module tb_top_iverilog $end
$var reg 1 ! pclk $end
$var reg 1 " presetn $end
$var reg 8 # paddr [7:0] $end
$var reg 1 $ pwrite $end
$var reg 1 % psel $end
$var reg 1 & penable $end
$var reg 32 ' pwdata [31:0] $end
$var reg 32 ( prdata [31:0] $end
$var reg 1 ) pready $end
$var reg 1 * pslverr $end
$var integer 32 + pass_count $end
$var integer 32 , fail_count $end
$var integer 32 - total_txns $end
$var integer 32 . cov_reg0_hits $end
$var integer 32 / cov_normal_reg_hits $end
$var integer 32 0 cov_readonly_hits $end
$var integer 32 1 cov_oob_hits $end
$var integer 32 2 cov_write_count $end
$var integer 32 3 cov_read_count $end
$var integer 32 4 cov_selfclear_bit_set $end
$var integer 32 5 cov_pslverr_seen $end
$var reg 32 6 rdata_capture [31:0] $end
$var reg 1 7 slverr_capture $end
$var reg 8 8 addr_capture [7:0] $end
$var reg 1 9 write_capture $end
$var reg 32 : wdata_capture [31:0] $end

$scope task apb_transfer $end
$upscope $end

$scope task check_txn $end
$upscope $end

$scope function gen_addr $end
$upscope $end

$scope module dut $end
$var parameter 32 ; ADDR_WIDTH $end
$var parameter 32 < DATA_WIDTH $end
$var parameter 32 = NUM_REGS $end
$var wire 1 > pclk $end
$var wire 1 ? presetn $end
$var wire 1 @ paddr [7] $end
$var wire 1 A paddr [6] $end
$var wire 1 B paddr [5] $end
$var wire 1 C paddr [4] $end
$var wire 1 D paddr [3] $end
$var wire 1 E paddr [2] $end
$var wire 1 F paddr [1] $end
$var wire 1 G paddr [0] $end
$var wire 1 H pwrite $end
$var wire 1 I psel $end
$var wire 1 J penable $end
$var wire 1 K pwdata [31] $end
$var wire 1 L pwdata [30] $end
$var wire 1 M pwdata [29] $end
$var wire 1 N pwdata [28] $end
$var wire 1 O pwdata [27] $end
$var wire 1 P pwdata [26] $end
$var wire 1 Q pwdata [25] $end
$var wire 1 R pwdata [24] $end
$var wire 1 S pwdata [23] $end
$var wire 1 T pwdata [22] $end
$var wire 1 U pwdata [21] $end
$var wire 1 V pwdata [20] $end
$var wire 1 W pwdata [19] $end
$var wire 1 X pwdata [18] $end
$var wire 1 Y pwdata [17] $end
$var wire 1 Z pwdata [16] $end
$var wire 1 [ pwdata [15] $end
$var wire 1 \ pwdata [14] $end
$var wire 1 ] pwdata [13] $end
$var wire 1 ^ pwdata [12] $end
$var wire 1 _ pwdata [11] $end
$var wire 1 ` pwdata [10] $end
$var wire 1 a pwdata [9] $end
$var wire 1 b pwdata [8] $end
$var wire 1 c pwdata [7] $end
$var wire 1 d pwdata [6] $end
$var wire 1 e pwdata [5] $end
$var wire 1 f pwdata [4] $end
$var wire 1 g pwdata [3] $end
$var wire 1 h pwdata [2] $end
$var wire 1 i pwdata [1] $end
$var wire 1 j pwdata [0] $end
$var reg 32 k prdata [31:0] $end
$var reg 1 l pready $end
$var reg 1 m pslverr $end
$var reg 2 n self_clear_cnt [1:0] $end
$var wire 1 o reg_idx [3] $end
$var wire 1 p reg_idx [2] $end
$var wire 1 q reg_idx [1] $end
$var wire 1 r reg_idx [0] $end
$var wire 1 s in_range $end
$upscope $end
$upscope $end
$enddefinitions $end
#0
$dumpvars
0!
0"
b0 #
0$
0%
0&
b0 '
b0 (
1)
0*
b0 k
1l
0m
b0 n
bx 6
x7
bx 8
x9
bx :
b1000 ;
b100000 <
b10000 =
b0 +
b0 ,
b0 -
b0 .
b0 /
b0 0
b0 1
b0 2
b0 3
b0 4
b0 5
0r
0q
0p
0o
1s
0>
0?
0G
0F
0E
0D
0C
0B
0A
0@
0H
0I
0J
0j
0i
0h
0g
0f
0e
0d
0c
0b
0a
0`
0_
0^
0]
0\
0[
0Z
0Y
0X
0W
0V
0U
0T
0S
0R
0Q
0P
0O
0N
0M
0L
0K
$end
#5
1!
1>
#10
0!
0>
#15
1!
1>
#20
0!
0>
#25
1!
1>
#30
0!
0>
#35
1!
1>
#40
0!
0>
#45
1!
1>
1"
1?
#50
0!
0>
#55
1!
1>
#60
0!
0>
#65
1!
1>
#70
0!
0>
#75
1!
1>
b1000 8
09
b1111000110011111010100110000 :
#80
0!
0>
#85
1!
1>
1%
b1000 #
1I
1D
1q
#90
0!
0>
#95
1!
1>
1&
1J
#100
0!
0>
#105
1!
1>
#106
b0 6
07
b1 -
b1 3
b1 /
b1 +
b1000000 8
b1011011111001001001110011011111 :
0%
0&
0I
0J
#110
0!
0>
#115
1!
1>
1%
b1000000 #
1I
0D
1A
0s
0q
#120
0!
0>
#125
1!
1>
1&
1J
#130
0!
0>
#135
1!
1>
1m
1*
#136
17
b10 -
b10 3
b1 5
b1 1
b10 +
b101100 8
19
b101011010011100100000001000000 :
0%
0&
0I
0J
#140
0!
0>
#145
1!
1>
0m
1%
b101100 #
1$
b101011010011100100000001000000 '
0*
1I
1H
1d
1\
1Y
1X
1W
1T
1R
1Q
1O
1M
1E
1D
1B
0A
1s
1r
1q
1o
#150
0!
0>
#155
1!
1>
1&
1J
#160
0!
0>
#165
1!
1>
#166
07
b11 -
b1 2
b10 /
b11 +
b1000100 8
09
b10100100111111111001010001011101 :
0%
0&
0I
0J
#170
0!
0>
#175
1!
1>
1%
b1000100 #
0$
b0 '
1I
0H
0d
0\
0Y
0X
0W
0T
0R
0Q
0O
0M
0D
0B
1A
0s
0q
0o
#180
0!
0>
#185
1!
1>
1&
1J
#190
0!
0>
#195
1!
1>
1m
1*
#196
17
b100 -
b11 3
b10 5
b10 1
b100 +
b1000000 8
b111001101110011010100111111 :
0%
0&
0I
0J
#200
0!
0>
#205
1!
1>
0m
1%
b1000000 #
0*
1I
0E
0r
#210
0!
0>
#215
1!
1>
1&
1J
#220
0!
0>
#225
1!
1>
1m
1*
#226
b101 -
b100 3
b11 5
b11 1
b101 +
b0 8
b101101000000101100010000100101 :
0%
0&
0I
0J
#230
0!
0>
#235
1!
1>
0m
1%
b0 #
0*
1I
0A
1s
#240
0!
0>
#245
1!
1>
1&
1J
#250
0!
0>
#255
1!
1>
#256
07
b110 -
b101 3
b1 .
b110 +
b101100 8
b11100100011110101110011100110001 :
0%
0&
0I
0J
#260
0!
0>
#265
1!
1>
1%
b101100 #
1I
1E
1D
1B
1r
1q
1o
#270
0!
0>
#275
1!
1>
1&
1J
#280
0!
0>
#285
1!
1>
b101011010011100100000001000000 k
b101011010011100100000001000000 (
#286
b101011010011100100000001000000 6
b111 -
b110 3
b11 /
b111 +
b10000 8
19
b10111110010110100001011011101010 :
0%
0&
0I
0J
#290
0!
0>
#295
1!
1>
1%
b10000 #
1$
b10111110010110100001011011101010 '
1I
1H
1i
1g
1e
1d
1c
1a
1`
1^
1Y
1W
1V
1T
1Q
1P
1O
1N
1M
1K
0E
0D
1C
0B
0r
0q
1p
0o
#300
0!
0>
#305
1!
1>
1&
1J
#310
0!
0>
#315
1!
1>
#316
b1000 -
b10 2
b100 /
b1000 +
b11000 8
09
b10110011111010010100001010101 :
0%
0&
0I
0J
#320
0!
0>
#325
1!
1>
1%
b11000 #
0$
b0 '
1I
0H
0i
0g
0e
0d
0c
0a
0`
0^
0Y
0W
0V
0T
0Q
0P
0O
0N
0M
0K
1D
1q
#330
0!
0>
#335
1!
1>
1&
1J
#340
0!
0>
#345
1!
1>
b0 k
b0 (
#346
b0 6
b1001 -
b111 3
b101 /
b1001 +
b100000 8
b110100010011000001101110000001 :
0%
0&
0I
0J
#350
0!
0>
#355
1!
1>
1%
b100000 #
1I
0D
0C
1B
0q
0p
1o
#360
0!
0>
#365
1!
1>
1&
1J
#370
0!
0>
#375
1!
1>
#376
b1010 -
b1000 3
b110 /
b1010 +
b111100 8
b10001111011001100000101111011001 :
0%
0&
0I
0J
#380
0!
0>
#385
1!
1>
1%
b111100 #
1I
1E
1D
1C
1r
1q
1p
#390
0!
0>
#395
1!
1>
1&
1J
#400
0!
0>
#405
1!
1>
#406
b1011 -
b1001 3
b1 0
b1011 +
b110100 8
b10011001111000001010011101001011 :
0%
0&
0I
0J
#410
0!
0>
#415
1!
1>
1%
b110100 #
1I
0D
0q
#420
0!
0>
#425
1!
1>
1&
1J
#430
0!
0>
#435
1!
1>
#436
b1100 -
b1010 3
b111 /
b1100 +
b0 8
b11101111001111101110111101001100 :
0%
0&
0I
0J
#440
0!
0>
#445
1!
1>
1%
b0 #
1I
0E
0C
0B
0r
0p
0o
#450
0!
0>
#455
1!
1>
1&
1J
#460
0!
0>
#465
1!
1>
#466
b1101 -
b1011 3
b10 .
b1101 +
b111100 8
19
b1111111011100010001101100010110 :
0%
0&
0I
0J
#470
0!
0>
#475
1!
1>
1%
b111100 #
1$
b1111111011100010001101100010110 '
1I
1H
1i
1h
1f
1b
1a
1_
1^
1Z
1V
1U
1T
1R
1Q
1P
1O
1N
1M
1L
1E
1D
1C
1B
1r
1q
1p
1o
#480
0!
0>
#485
1!
1>
1&
1J
#490
0!
0>
#495
1!
1>
#496
b1110 -
b11 2
b10 0
b1110 +
b1000 8
b11000100001001101111001001000101 :
0%
0&
0I
0J
#500
0!
0>
#505
1!
1>
1%
b1000 #
b11000100001001101111001001000101 '
1I
1j
0i
0f
1d
0b
0_
1]
1\
1[
0Z
1Y
1X
0V
0T
0R
0Q
0O
0N
0M
1K
0E
0C
0B
0r
0p
0o
#510
0!
0>
#515
1!
1>
1&
1J
#520
0!
0>
#525
1!
1>
#526
b1111 -
b100 2
b1000 /
b1111 +
b111100 8
09
b11100110010100010011101001111000 :
0%
0&
0I
0J
#530
0!
0>
#535
1!
1>
1%
b111100 #
0$
b0 '
1I
0H
0j
0h
0d
0a
0^
0]
0\
0[
0Y
0X
0U
0P
0L
0K
1E
1C
1B
1r
1p
1o
#540
0!
0>
#545
1!
1>
1&
1J
#550
0!
0>
#555
1!
1>
#556
b10000 -
b1100 3
b11 0
b10000 +
b11100 8
19
b1100010110111011110100000101 :
0%
0&
0I
0J
#560
0!
0>
#565
1!
1>
1%
b11100 #
1$
b1100010110111011110100000101 '
1I
1H
1j
1h
1b
1`
1_
1^
1]
1[
1Z
1Y
1W
1V
1T
1P
1O
0B
0o
#570
0!
0>
#575
1!
1>
1&
1J
#580
0!
0>
#585
1!
1>
#586
b10001 -
b101 2
b1001 /
b10001 +
b100 8
b100000001011000110101110001000 :
0%
0&
0I
0J
#590
0!
0>
#595
1!
1>
1%
b100 #
b100000001011000110101110001000 '
1I
0j
0h
1g
1c
1a
0`
0^
1\
0[
0Z
0Y
1X
0V
1U
0T
0P
0O
1M
0D
0C
0q
0p
#600
0!
0>
#605
1!
1>
1&
1J
#610
0!
0>
#615
1!
1>
#616
b10010 -
b110 2
b1010 /
b10010 +
b110000 8
09
b11010101100100001001110100001100 :
0%
0&
0I
0J
#620
0!
0>
#625
1!
1>
1%
b110000 #
0$
b0 '
1I
0H
0g
0c
0b
0a
0_
0]
0\
0X
0W
0U
0M
0E
1C
1B
0r
1p
1o
#630
0!
0>
#635
1!
1>
1&
1J
#640
0!
0>
#645
1!
1>
#646
b10011 -
b1101 3
b1011 /
b10011 +
b1000100 8
b1001000110111111010011100011100 :
0%
0&
0I
0J
#650
0!
0>
#655
1!
1>
1%
b1000100 #
1I
1E
0C
0B
1A
0s
1r
0p
0o
#660
0!
0>
#665
1!
1>
1&
1J
#670
0!
0>
#675
1!
1>
1m
1*
#676
17
b10100 -
b1110 3
b100 5
b100 1
b10100 +
b11100 8
b10010011101110010110101011110101 :
0%
0&
0I
0J
#680
0!
0>
#685
1!
1>
0m
1%
b11100 #
0*
1I
1D
1C
0A
1s
1q
1p
#690
0!
0>
#695
1!
1>
1&
1J
#700
0!
0>
#705
1!
1>
b1100010110111011110100000101 k
b1100010110111011110100000101 (
#706
b1100010110111011110100000101 6
07
b10101 -
b1111 3
b1100 /
b10101 +
b0 8
19
b10100111010011110100110100101110 :
0%
0&
0I
0J
#710
0!
0>
#715
1!
1>
1%
b0 #
1$
b10100111010011110100110100101110 '
1I
1H
1i
1h
1g
1e
1b
1`
1_
1\
1Z
1Y
1X
1W
1T
1R
1Q
1P
1M
1K
0E
0D
0C
0r
0q
0p
#720
0!
0>
#725
1!
1>
1&
1J
#730
0!
0>
#735
1!
1>
b10 n
#736
b10110 -
b111 2
b11 .
b1 4
b10110 +
b111100 8
b10111010011110100010010001011110 :
0%
0&
0I
0J
#740
0!
0>
#745
1!
1>
b1 n
1%
b111100 #
b10111010011110100010010001011110 '
1I
1f
0e
1d
0b
0_
1]
0\
0Z
0X
1V
1U
0R
0P
1O
1N
1E
1D
1C
1B
1r
1q
1p
1o
#750
0!
0>
#755
1!
1>
b0 n
1&
1J
#760
0!
0>
#765
1!
1>
#766
b10111 -
b1000 2
b100 0
b10111 +
b10000 8
b10100110011001010110001110010100 :
0%
0&
0I
0J
#770
0!
0>
#775
1!
1>
1%
b10000 #
b10100110011001010110001110010100 '
1I
0i
0g
0d
1c
1b
1a
0`
1\
1Z
0Y
1X
0W
0V
1P
0O
0N
0E
0D
0B
0r
0q
0o
#780
0!
0>
#785
1!
1>
1&
1J
#790
0!
0>
#795
1!
1>
#796
b11000 -
b1001 2
b1101 /
b11000 +
b111000 8
b10000111101100101110000110110101 :
0%
0&
0I
0J
#800
0!
0>
#805
1!
1>
1%
b111000 #
b10000111101100101110000110110101 '
1I
1j
1e
0a
1[
0Z
1Y
0X
1V
0T
1S
1R
0M
1D
1B
1q
1o
#810
0!
0>
#815
1!
1>
1&
1J
#820
0!
0>
#825
1!
1>
#826
b11001 -
b1010 2
b1110 /
b11001 +
b111100 8
09
b11011100111010000101011011110111 :
0%
0&
0I
0J
#830
0!
0>
#835
1!
1>
1%
b111100 #
0$
b0 '
1I
0H
0j
0h
0f
0e
0c
0b
0]
0\
0[
0Y
0V
0U
0S
0R
0Q
0P
0K
1E
1r
#840
0!
0>
#845
1!
1>
1&
1J
#850
0!
0>
#855
1!
1>
b0 k
b0 (
#856
b0 6
b11010 -
b10000 3
b101 0
b11010 +
b100 8
b10000010100100101110110101010001 :
0%
0&
0I
0J
#860
0!
0>
#865
1!
1>
1%
b100 #
1I
0D
0C
0B
0q
0p
0o
#870
0!
0>
#875
1!
1>
1&
1J
#880
0!
0>
#885
1!
1>
b100000001011000110101110001000 k
b100000001011000110101110001000 (
#886
b100000001011000110101110001000 6
b11011 -
b10001 3
b1111 /
b11011 +
b1000100 8
b11010011101010000010001110101110 :
0%
0&
0I
0J
#890
0!
0>
#895
1!
1>
1%
b1000100 #
1I
1A
0s
#900
0!
0>
#905
1!
1>
1&
1J
#910
0!
0>
#915
1!
1>
1m
1*
#916
17
b11100 -
b10010 3
b101 5
b101 1
b11100 +
b110100 8
19
b1010000101010010010101011110 :
0%
0&
0I
0J
#920
0!
0>
#925
1!
1>
0m
1%
b110100 #
1$
b1010000101010010010101011110 '
0*
1I
1H
1i
1h
1g
1f
1d
1b
1`
1]
1Z
1X
1V
1Q
1O
1C
1B
0A
1s
1p
1o
#930
0!
0>
#935
1!
1>
1&
1J
#940
0!
0>
#945
1!
1>
#946
07
b11101 -
b1011 2
b10000 /
b11101 +
b10000 8
09
b1111010011100101010000111010011 :
0%
0&
0I
0J
#950
0!
0>
#955
1!
1>
1%
b10000 #
0$
b0 '
1I
0H
0i
0h
0g
0f
0d
0b
0`
0]
0Z
0X
0V
0Q
0O
0E
0B
0r
0o
#960
0!
0>
#965
1!
1>
1&
1J
#970
0!
0>
#975
1!
1>
b10100110011001010110001110010100 k
b10100110011001010110001110010100 (
#976
b10100110011001010110001110010100 6
b11110 -
b10011 3
b10001 /
b11110 +
b100 8
b11011000111110111000000100110010 :
0%
0&
0I
0J
#980
0!
0>
#985
1!
1>
1%
b100 #
1I
1E
0C
1r
0p
#990
0!
0>
#995
1!
1>
1&
1J
#1000
0!
0>
#1005
1!
1>
b100000001011000110101110001000 k
b100000001011000110101110001000 (
#1006
b100000001011000110101110001000 6
b11111 -
b10100 3
b10010 /
b11111 +
b0 8
19
b1111101001011110011011100111 :
0%
0&
0I
0J
#1010
0!
0>
#1015
1!
1>
1%
b0 #
1$
b1111101001011110011011100111 '
1I
1H
1j
1i
1h
1e
1d
1c
1a
1`
1]
1\
1[
1Z
1X
1U
1S
1R
1Q
1P
1O
0E
0r
#1020
0!
0>
#1025
1!
1>
1&
1J
#1030
0!
0>
#1035
1!
1>
#1036
b100000 -
b1100 2
b100 .
b100000 +
b111100 8
b100001101001110101011110111000 :
0%
0&
0I
0J
#1040
0!
0>
#1045
1!
1>
1%
b111100 #
b100001101001110101011110111000 '
1I
0j
0i
0h
1g
1f
0d
1b
1^
0]
0[
1Y
0Q
0P
0O
1M
1E
1D
1C
1B
1r
1q
1p
1o
#1050
0!
0>
#1055
1!
1>
1&
1J
#1060
0!
0>
#1065
1!
1>
#1066
b100001 -
b1101 2
b110 0
b100001 +
b100100 8
09
b11010000000011011001001110100010 :
0%
0&
0I
0J
#1070
0!
0>
#1075
1!
1>
1%
b100100 #
0$
b0 '
1I
0H
0g
0f
0e
0c
0b
0a
0`
0^
0\
0Z
0Y
0X
0U
0S
0R
0M
0D
0C
0q
0p
#1080
0!
0>
#1085
1!
1>
1&
1J
#1090
0!
0>
#1095
1!
1>
b0 k
b0 (
#1096
b0 6
b100010 -
b10101 3
b10011 /
b100010 +
b1000 8
b1101011011011100110010100001 :
0%
0&
0I
0J
#1100
0!
0>
#1105
1!
1>
1%
b1000 #
1I
0E
1D
0B
0r
1q
0o
#1110
0!
0>
#1115
1!
1>
1&
1J
#1120
0!
0>
#1125
1!
1>
b11000100001001101111001001000101 k
b11000100001001101111001001000101 (
#1126
b11000100001001101111001001000101 6
b100011 -
b10110 3
b10100 /
b100011 +
b110000 8
b10011011010011011111101011111010 :
0%
0&
0I
0J
#1130
0!
0>
#1135
1!
1>
1%
b110000 #
1I
0D
1C
1B
0q
1p
1o
#1140
0!
0>
#1145
1!
1>
1&
1J
#1150
0!
0>
#1155
1!
1>
b0 k
b0 (
#1156
b0 6
b100100 -
b10111 3
b10101 /
b100100 +
b0 8
19
b11101101101010010001010001110011 :
0%
0&
0I
0J
#1160
0!
0>
#1165
1!
1>
1%
b0 #
1$
b11101101101010010001010001110011 '
1I
1H
1j
1i
1f
1e
1d
1`
1^
1Z
1W
1U
1S
1R
1P
1O
1M
1L
1K
0C
0B
0p
0o
#1170
0!
0>
#1175
1!
1>
1&
1J
#1180
0!
0>
#1185
1!
1>
b10 n
#1186
b100101 -
b1110 2
b101 .
b10 4
b100101 +
b10000 8
09
b10010000110001011010011100111001 :
0%
0&
0I
0J
#1190
0!
0>
#1195
1!
1>
b1 n
1%
b10000 #
0$
b0 '
1I
0H
0j
0i
0f
0e
0d
0`
0^
0Z
0W
0U
0S
0R
0P
0O
0M
0L
0K
1C
1p
#1200
0!
0>
#1205
1!
1>
b0 n
1&
1J
#1210
0!
0>
#1215
1!
1>
b10100110011001010110001110010100 k
b10100110011001010110001110010100 (
#1216
b10100110011001010110001110010100 6
b100110 -
b11000 3
b10110 /
b100110 +
b100100 8
b11110001111001011000011001000111 :
0%
0&
0I
0J
#1220
0!
0>
